adafruit_ads1x15/__init__.py
adafruit_ads1x15/ads1015.py
adafruit_ads1x15/ads1115.py
adafruit_ads1x15/ads1x15.py
adafruit_ads1x15/analog_in.py
adafruit_ads1x15/py.typed
adafruit_circuitpython_ads1x15-3.0.1.dist-info/licenses/LICENSE
adafruit_circuitpython_ads1x15-3.0.1.dist-info/METADATA
adafruit_circuitpython_ads1x15-3.0.1.dist-info/WHEEL
adafruit_circuitpython_ads1x15-3.0.1.dist-info/top_level.txt
adafruit_circuitpython_ads1x15-3.0.1.dist-info/RECORD
