Metadata-Version: 2.4
Name: adafruit-circuitpython-ads1x15
Version: 3.0.1
Summary: CircuitPython library for controlling an ADS1x15 ADC.
Author-email: Adafruit Industries <circuitpython@adafruit.com>
License: MIT
Project-URL: Homepage, https://github.com/adafruit/Adafruit_CircuitPython_ADS1x15
Keywords: adafruit,ads1x115,adc,hardware,micropython,circuitpython
Classifier: Intended Audience :: Developers
Classifier: Topic :: Software Development :: Libraries
Classifier: Topic :: Software Development :: Embedded Systems
Classifier: Topic :: System :: Hardware
Classifier: License :: OSI Approved :: MIT License
Classifier: Programming Language :: Python :: 3
License-File: LICENSE
Requires-Dist: Adafruit-Blinka
Requires-Dist: adafruit-circuitpython-busdevice
Requires-Dist: typing-extensions~=4.0
Provides-Extra: optional
Dynamic: license-file
